{"stored_at": "2025-12-05T22:36:39.116246+00:00", "stored_kind": "raw", "data": "{\"schema\":{\"fields\":[{\"name\":\"index\",\"type\":\"integer\"},{\"name\":\"time_tag\",\"type\":\"string\"},{\"name\":\"dst\",\"type\":\"number\"}],\"primaryKey\":[\"index\"],\"pandas_version\":\"1.4.0\"},\"data\":[{\"index\":0,\"time_tag\":\"2025-12-05T21:36:00\",\"dst\":-8.5401897},{\"index\":1,\"time_tag\":\"2025-12-05T21:37:00\",\"dst\":-8.7123299},{\"index\":2,\"time_tag\":\"2025-12-05T21:38:00\",\"dst\":-8.6347399},{\"index\":3,\"time_tag\":\"2025-12-05T21:39:00\",\"dst\":-8.5679302},{\"index\":4,\"time_tag\":\"2025-12-05T21:40:00\",\"dst\":-8.8403797},{\"index\":5,\"time_tag\":\"2025-12-05T21:41:00\",\"dst\":-9.2513504},{\"index\":6,\"time_tag\":\"2025-12-05T21:42:00\",\"dst\":-8.4310198},{\"index\":7,\"time_tag\":\"2025-12-05T21:43:00\",\"dst\":-8.5331097},{\"index\":8,\"time_tag\":\"2025-12-05T21:44:00\",\"dst\":-9.7315102},{\"index\":9,\"time_tag\":\"2025-12-05T21:45:00\",\"dst\":-10.9481},{\"index\":10,\"time_tag\":\"2025-12-05T21:46:00\",\"dst\":-11.9481},{\"index\":11,\"time_tag\":\"2025-12-05T21:47:00\",\"dst\":-10.7967},{\"index\":12,\"time_tag\":\"2025-12-05T21:48:00\",\"dst\":-10.0543},{\"index\":13,\"time_tag\":\"2025-12-05T21:49:00\",\"dst\":-9.2696104},{\"index\":14,\"time_tag\":\"2025-12-05T21:50:00\",\"dst\":-8.8644896},{\"index\":15,\"time_tag\":\"2025-12-05T21:51:00\",\"dst\":-8.5992403},{\"index\":16,\"time_tag\":\"2025-12-05T21:52:00\",\"dst\":-8.5481796},{\"index\":17,\"time_tag\":\"2025-12-05T21:53:00\",\"dst\":-9.2339201},{\"index\":18,\"time_tag\":\"2025-12-05T21:54:00\",\"dst\":-10.18},{\"index\":19,\"time_tag\":\"2025-12-05T21:55:00\",\"dst\":-11.2132},{\"index\":20,\"time_tag\":\"2025-12-05T21:56:00\",\"dst\":-11.1551},{\"index\":21,\"time_tag\":\"2025-12-05T21:57:00\",\"dst\":-11.108},{\"index\":22,\"time_tag\":\"2025-12-05T21:58:00\",\"dst\":-11.5655},{\"index\":23,\"time_tag\":\"2025-12-05T21:59:00\",\"dst\":-12.2284},{\"index\":24,\"time_tag\":\"2025-12-05T22:00:00\",\"dst\":-12.8246},{\"index\":25,\"time_tag\":\"2025-12-05T22:01:00\",\"dst\":-13.6212},{\"index\":26,\"time_tag\":\"2025-12-05T22:02:00\",\"dst\":-14.4307},{\"index\":27,\"time_tag\":\"2025-12-05T22:03:00\",\"dst\":-14.105},{\"index\":28,\"time_tag\":\"2025-12-05T22:04:00\",\"dst\":-13.538},{\"index\":29,\"time_tag\":\"2025-12-05T22:05:00\",\"dst\":-13.8451},{\"index\":30,\"time_tag\":\"2025-12-05T22:06:00\",\"dst\":-14.5401},{\"index\":31,\"time_tag\":\"2025-12-05T22:07:00\",\"dst\":-14.4252},{\"index\":32,\"time_tag\":\"2025-12-05T22:08:00\",\"dst\":-14.7515},{\"index\":33,\"time_tag\":\"2025-12-05T22:09:00\",\"dst\":-14.8615},{\"index\":34,\"time_tag\":\"2025-12-05T22:10:00\",\"dst\":-12.9376},{\"index\":35,\"time_tag\":\"2025-12-05T22:11:00\",\"dst\":-11.7774},{\"index\":36,\"time_tag\":\"2025-12-05T22:12:00\",\"dst\":-10.813},{\"index\":37,\"time_tag\":\"2025-12-05T22:13:00\",\"dst\":-12.3403},{\"index\":38,\"time_tag\":\"2025-12-05T22:14:00\",\"dst\":-14.3769},{\"index\":39,\"time_tag\":\"2025-12-05T22:15:00\",\"dst\":-15.5894},{\"index\":40,\"time_tag\":\"2025-12-05T22:16:00\",\"dst\":-16.4007},{\"index\":41,\"time_tag\":\"2025-12-05T22:17:00\",\"dst\":-14.5107},{\"index\":42,\"time_tag\":\"2025-12-05T22:18:00\",\"dst\":-5.85886},{\"index\":43,\"time_tag\":\"2025-12-05T22:19:00\",\"dst\":0.156792},{\"index\":44,\"time_tag\":\"2025-12-05T22:20:00\",\"dst\":-5.9545598},{\"index\":45,\"time_tag\":\"2025-12-05T22:21:00\",\"dst\":-12.3337},{\"index\":46,\"time_tag\":\"2025-12-05T22:22:00\",\"dst\":-14.3958},{\"index\":47,\"time_tag\":\"2025-12-05T22:23:00\",\"dst\":-13.9927},{\"index\":48,\"time_tag\":\"2025-12-05T22:24:00\",\"dst\":-13.1903},{\"index\":49,\"time_tag\":\"2025-12-05T22:25:00\",\"dst\":-12.6158},{\"index\":50,\"time_tag\":\"2025-12-05T22:26:00\",\"dst\":-12.2332},{\"index\":51,\"time_tag\":\"2025-12-05T22:27:00\",\"dst\":-12.1659},{\"index\":52,\"time_tag\":\"2025-12-05T22:28:00\",\"dst\":-11.7045},{\"index\":53,\"time_tag\":\"2025-12-05T22:29:00\",\"dst\":-10.7234},{\"index\":54,\"time_tag\":\"2025-12-05T22:30:00\",\"dst\":-10.3692},{\"index\":55,\"time_tag\":\"2025-12-05T22:31:00\",\"dst\":-10.6348},{\"index\":56,\"time_tag\":\"2025-12-05T22:32:00\",\"dst\":-11.5173}]}"}